findpeaks/__init__.py
findpeaks/examples.py
findpeaks/findpeaks.py
findpeaks/interpolate.py
findpeaks/peakdetect.py
findpeaks/stats.py
findpeaks/union_find.py
findpeaks/data/__init__.py
findpeaks/filters/__init__.py
findpeaks/filters/frost.py
findpeaks/filters/kuan.py
findpeaks/filters/lee.py
findpeaks/filters/lee_enhanced.py
findpeaks/filters/lee_sigma.py
findpeaks/filters/mean.py
findpeaks/filters/median.py
findpeaks/tests/__init__.py
findpeaks/tests/test_findpeaks.py
findpeaks-2.7.5.dist-info/licenses/LICENSE
findpeaks-2.7.5.dist-info/METADATA
findpeaks-2.7.5.dist-info/WHEEL
findpeaks-2.7.5.dist-info/top_level.txt
findpeaks-2.7.5.dist-info/RECORD
