Metadata-Version: 2.4
Name: findpeaks
Version: 2.7.5
Summary: findpeaks is for the detection of peaks and valleys in a 1D vector and 2D array (image).
Author-email: Erdogan Taskesen <erdogant@gmail.com>
License-Expression: MIT
Project-URL: Homepage, https://erdogant.github.io/findpeaks
Project-URL: Download, https://github.com/erdogant/findpeaks/archive/{version}.tar.gz
Keywords: Python,peak detection,valley detection,image processing,signal processing,topology,topological data analysis,TDA,denoising,speckle noise removal,feature extraction,1D signal,2D array,image analysis,findpeaks,peak analysis,data analysis,scientific computing
Classifier: Programming Language :: Python :: 3
Classifier: Operating System :: OS Independent
Classifier: Intended Audience :: Education
Classifier: Intended Audience :: Science/Research
Classifier: Operating System :: Unix
Classifier: Operating System :: Microsoft :: Windows
Classifier: Operating System :: MacOS
Requires-Python: >=3
License-File: LICENSE
Requires-Dist: scipy
Requires-Dist: matplotlib
Requires-Dist: numpy
Requires-Dist: pandas
Requires-Dist: tqdm
Requires-Dist: requests
Requires-Dist: caerus>=1.0.1
Requires-Dist: xarray
Requires-Dist: joblib
Requires-Dist: adjustText
Requires-Dist: opencv-python-headless
Dynamic: license-file
